{
	"configurations" : 
	[
		{
			"directories" : 
			[
				{
					"build" : ".",
					"jsonFile" : "directory-.-Debug-d0094a50bb2071803777.json",
					"minimumCMakeVersion" : 
					{
						"string" : "3.1"
					},
					"projectIndex" : 0,
					"source" : ".",
					"targetIndexes" : 
					[
						0
					]
				}
			],
			"name" : "Debug",
			"projects" : 
			[
				{
					"directoryIndexes" : 
					[
						0
					],
					"name" : "My_mini_world",
					"targetIndexes" : 
					[
						0
					]
				}
			],
			"targets" : 
			[
				{
					"directoryIndex" : 0,
					"id" : "My_mini_world::@6890427a1f51a3e7e1df",
					"jsonFile" : "target-My_mini_world-Debug-60dcaac7011162c0a867.json",
					"name" : "My_mini_world",
					"projectIndex" : 0
				}
			]
		}
	],
	"kind" : "codemodel",
	"paths" : 
	{
		"build" : "D:/Coding/My_mini_world/cmake-build-debug",
		"source" : "D:/Coding/My_mini_world"
	},
	"version" : 
	{
		"major" : 2,
		"minor" : 4
	}
}
